LICENSE
los_docusign/__init__.py
los_docusign/admin.py
los_docusign/apps.py
los_docusign/asgi.py
los_docusign/migrations/0001_initial.py
los_docusign/migrations/0002_auto_20211125_0208.py
los_docusign/migrations/0003_auto_20211227_1445.py
los_docusign/migrations/0004_auto_20220119_1610.py
los_docusign/migrations/0005_docusignenvelopeauditlog_recipient_details.py
los_docusign/migrations/0006_remove_docusignuserauth_two_factor_enabled_flag.py
los_docusign/migrations/0007_alter_docusignenvelopestagedata_error_message.py
los_docusign/migrations/0008_auto_20230412_2119.py
los_docusign/migrations/__init__.py
los_docusign/models.py
los_docusign/tests.py
los_docusign/urls.py
los_docusign/utils/XmlParser.py
los_docusign/utils/__init__.py
los_docusign/utils/api_handler.py
los_docusign/utils/client.py
los_docusign/utils/docusign_adapter.py
los_docusign/utils/docusign_helper.py
los_docusign/utils/validators.py
los_docusign/views.py
los_docusign/wsgi.py
los_docusign-0.6.7.dist-info/LICENSE
los_docusign-0.6.7.dist-info/METADATA
los_docusign-0.6.7.dist-info/WHEEL
los_docusign-0.6.7.dist-info/RECORD
