Metadata-Version: 2.1
Name: los-docusign
Version: 0.6.7
Summary: Docusign Django Wrapper for integrating DocuSign with Django Application
Home-page: https://github.com/Lenders-Cooperative/Django-DocuSign
License: BSD-3-Clause
Author: tejasb
Author-email: tejas@thesummitgrp.com
Requires-Python: >=3.10.2,<4.0.0
Classifier: License :: OSI Approved :: BSD License
Classifier: Programming Language :: Python :: 3
Classifier: Programming Language :: Python :: 3.11
Requires-Dist: Django (==3.2.15)
Requires-Dist: PyJWT (==2.4)
Requires-Dist: black (==22.3.0)
Requires-Dist: django-environ (>=0.4.5,<0.5.0)
Requires-Dist: django-lc-utils (>=0.2.1,<0.3.0)
Requires-Dist: django-model-utils (>=4.1.1,<5.0.0)
Requires-Dist: django-utils-six (>=2.0,<3.0)
Requires-Dist: docusign-esign (>=3.6.0,<4.0.0)
Requires-Dist: phonenumbers (==8.12.26)
Requires-Dist: requests (>=2.26.0,<3.0.0)
